jupyterlab_kernel_usage/__init__.py
jupyterlab_kernel_usage/_version.py
jupyterlab_kernel_usage/handlers.py
jupyterlab_kernel_usage/labextension/build_log.json
jupyterlab_kernel_usage/labextension/package.json
jupyterlab_kernel_usage/labextension/static/lib_index_js.55836a5659ad18a8e256.js
jupyterlab_kernel_usage/labextension/static/lib_index_js.55836a5659ad18a8e256.js.map
jupyterlab_kernel_usage/labextension/static/remoteEntry.7c0bd21b4d29b79cdbad.js
jupyterlab_kernel_usage/labextension/static/remoteEntry.7c0bd21b4d29b79cdbad.js.map
jupyterlab_kernel_usage/labextension/static/style.js
jupyterlab_kernel_usage/labextension/static/style_index_js.dd18dd2c012eb5ab6444.js
jupyterlab_kernel_usage/labextension/static/style_index_js.dd18dd2c012eb5ab6444.js.map
jupyterlab_kernel_usage/labextension/static/vendors-node_modules_css-loader_dist_runtime_api_js-node_modules_css-loader_dist_runtime_cssW-72eba1.8d429423f50ae685f348.js
jupyterlab_kernel_usage/labextension/static/vendors-node_modules_css-loader_dist_runtime_api_js-node_modules_css-loader_dist_runtime_cssW-72eba1.8d429423f50ae685f348.js.map
jupyterlab_kernel_usage-0.6.0.data/data/etc/jupyter/jupyter_notebook_config.d/jupyterlab_kernel_usage.json
jupyterlab_kernel_usage-0.6.0.data/data/etc/jupyter/jupyter_server_config.d/jupyterlab_kernel_usage.json
jupyterlab_kernel_usage-0.6.0.data/data/share/jupyter/labextensions/jupyterlab-kernel-usage/build_log.json
jupyterlab_kernel_usage-0.6.0.data/data/share/jupyter/labextensions/jupyterlab-kernel-usage/install.json
jupyterlab_kernel_usage-0.6.0.data/data/share/jupyter/labextensions/jupyterlab-kernel-usage/package.json
jupyterlab_kernel_usage-0.6.0.data/data/share/jupyter/labextensions/jupyterlab-kernel-usage/static/lib_index_js.55836a5659ad18a8e256.js
jupyterlab_kernel_usage-0.6.0.data/data/share/jupyter/labextensions/jupyterlab-kernel-usage/static/lib_index_js.55836a5659ad18a8e256.js.map
jupyterlab_kernel_usage-0.6.0.dist-info/LICENSE
jupyterlab_kernel_usage-0.6.0.dist-info/METADATA
jupyterlab_kernel_usage-0.6.0.dist-info/WHEEL
jupyterlab_kernel_usage-0.6.0.dist-info/top_level.txt
jupyterlab_kernel_usage-0.6.0.dist-info/RECORD
